repmt/__init__.py
repmt/cli.py
repmt/frontend.py
repmt/backend/__init__.py
repmt/backend/backend.py
repmt/backend/prompt_generator.py
repmt-0.1.5.dist-info/LICENSE
repmt-0.1.5.dist-info/METADATA
repmt-0.1.5.dist-info/WHEEL
repmt-0.1.5.dist-info/entry_points.txt
repmt-0.1.5.dist-info/top_level.txt
repmt-0.1.5.dist-info/RECORD
